scentamint-1.1.2.dist-info/RECORD
scentamint-1.1.2.dist-info/DESCRIPTION.rst
scentamint-1.1.2.dist-info/WHEEL
scentamint-1.1.2.dist-info/METADATA
scentamint-1.1.2.dist-info/entry_points.txt
scentamint-1.1.2.dist-info/metadata.json
scentamint-1.1.2.dist-info/top_level.txt
scentamint/config.py
scentamint/__init__.py
scentamint/server.py
scentamint/service/__init__.py
scentamint/data/scentamint.ini
