Metadata-Version: 2.0
Name: scentamint
Version: 1.1.2
Summary: A web api providing naïve bayesian text classification and training using simplebayes.
Home-page: https://github.com/hickeroar/scentamint
Author: Ryan Vennell
Author-email: ryan.vennell@gmail.com
License: MIT
Platform: UNKNOWN
Classifier: Development Status :: 5 - Production/Stable
Classifier: License :: OSI Approved :: MIT License
Classifier: Intended Audience :: Developers
Classifier: Programming Language :: Python
Classifier: Programming Language :: Python :: 2
Classifier: Programming Language :: Python :: 2.7
Classifier: Programming Language :: Python :: 3
Classifier: Programming Language :: Python :: 3.4
Classifier: Topic :: Utilities
Classifier: Operating System :: MacOS
Classifier: Operating System :: POSIX :: Linux
Requires-Dist: simplejson
Requires-Dist: simplebayes
Requires-Dist: flask
Requires-Dist: configparser
